requests_decorator/__init__.py
requests_decorator/exceptions.py
requests_decorator/requests.py
requests_decorator/responses.py
requests_decorator/router.py
requests_decorator/utils.py
requests_decorator-0.1.0.dist-info/WHEEL
requests_decorator-0.1.0.dist-info/METADATA
requests_decorator-0.1.0.dist-info/RECORD
