Metadata-Version: 2.1
Name: requests-decorator
Version: 0.1.0
Summary: Python HTTP for (lazy) humans.
Author: conor-od
Author-email: codonnell872@gmail.com
Requires-Python: >=3.9,<4.0
Classifier: Programming Language :: Python :: 3
Classifier: Programming Language :: Python :: 3.10
Classifier: Programming Language :: Python :: 3.9
Requires-Dist: pydantic (>=1.10.3,<2.0.0)
Requires-Dist: requests (>=2.28.1,<3.0.0)
